README.txt
setup.py
djangounchained_flash/__init__.py
djangounchained_flash.egg-info/PKG-INFO
djangounchained_flash.egg-info/SOURCES.txt
djangounchained_flash.egg-info/dependency_links.txt
djangounchained_flash.egg-info/not-zip-safe
djangounchained_flash.egg-info/top_level.txt