Metadata-Version: 1.0
Name: djangounchained-flash
Version: 1.2
Summary: Flash messaging for setup
Home-page: UNKNOWN
Author: Ashwin Mahesh
Author-email: mahesh2@purdue.edu
License: None
Platform: UNKNOWN
